README.md
setup.py
RePrIm/__init__.py
RePrIm/reprim.py
RePrIm/util/callback_io.py
RePrIm/util/hardware_monitor.py
RePrIm/util/lib.py
RePrIm/util/reprim_io.py
RePrIm/util/tools.py
RePrIm/util/callback_io.py
RePrIm/util/hardware_monitor.py
RePrIm/util/lib.py
RePrIm/util/reprim_io.py
RePrIm/util/tools.py
reprim.egg-info/PKG-INFO
reprim.egg-info/SOURCES.txt
reprim.egg-info/dependency_links.txt
reprim.egg-info/requires.txt
reprim.egg-info/top_level.txt