Metadata-Version: 2.1
Name: reprim
Version: 1.0.0
Summary: for questions write me in Telegram (@IDieLast)
Home-page: https://github.com/GGergy/RePrIm/
Author: GGergy
Author-email: gergy2k07@gmail.com
Classifier: Programming Language :: Python :: 3.11
Classifier: License :: OSI Approved :: GNU General Public License v3 (GPLv3)
